{"cameraMode":{"drawMode":0,"name":"Shaded","section":"Shading Mode"},"sceneLighting":false,"audioPlay":false,"sceneViewState":{"showFog":true,"showMaterialUpdate":false,"showSkybox":false,"showFlares":true,"showImageEffects":true,"showParticleSystems":true},"in2DMode":false,"pivot":{"x":0.011352062225341797,"y":1.2039645910263062,"z":-0.0975537896156311},"rotation":{"x":0.19002404808998109,"y":0.8001035451889038,"z":-0.468638151884079,"w":0.32466864585876467},"size":5.510569095611572,"orthographic":false}